windbgmon.py
windbgmon-0.1.1.dist-info/LICENSE
windbgmon-0.1.1.dist-info/METADATA
windbgmon-0.1.1.dist-info/WHEEL
windbgmon-0.1.1.dist-info/top_level.txt
windbgmon-0.1.1.dist-info/RECORD
